loglocal/__init__.py
loglocal/_loglocal.py
loglocal/_trace.py
loglocal/py.typed
loglocal/default/__init__.py
loglocal/models/__init__.py
loglocal/models/_config_models.py
loglocal-1.0.5.dist-info/METADATA
loglocal-1.0.5.dist-info/WHEEL
loglocal-1.0.5.dist-info/RECORD
