Metadata-Version: 2.4
Name: loglocal
Version: 1.0.5
Summary: A Python library for local logging with advanced features
Author-email: Mahamudul Hasan <919.hasan@gmail.com>
Requires-Python: >=3.11
Requires-Dist: loguru>=0.7.3
Requires-Dist: opentelemetry-api>=1.36.0
Requires-Dist: opentelemetry-sdk>=1.36.0
Requires-Dist: pydantic>=2.11.7
Requires-Dist: python-dotenv>=1.1.1
